sap_tool/__init__.py
sap_tool-0.1.4.dist-info/METADATA
sap_tool-0.1.4.dist-info/WHEEL
sap_tool-0.1.4.dist-info/top_level.txt
sap_tool-0.1.4.dist-info/RECORD
