Metadata-Version: 2.4
Name: sap-tool
Version: 0.1.4
Summary: A simple tool class for schema generation. Helps agents create schemas for methods/functions easily.
Author: Your Name
Author-email: rabeeqiblawi <rabeeqiblawi@gmail.com>
License-Expression: MIT
Requires-Python: >=3.7
